{
    "version": 12,
    "title": "Messenger Mod Update 😎",
    "message": "HELLO You have a NEW VERSION😉✌️",
    "url": "https://t.me/facebookpro_official",
    "isCancel": true,
    "crash": false,
    "shopee": "https://shope.ee/4AbKJZRlOC,https://shope.ee/40Hu7GSOjB,https://shope.ee/4VEAiBQUiI,https://shope.ee/4KukVsR83H,https://shope.ee/4pr16nPE2O,https://shope.ee/4fXauUPrNN,https://shope.ee/5ATrVPNxMU,https://shope.ee/50ARJ6OahT,https://shope.ee/2q5wj7Wq64,https://shope.ee/2fmWWoXTR3,https://shope.ee/3Ain7jVZQA,https://shope.ee/30PMvQWCl9,https://shope.ee/3VLdWLUIkG,https://shope.ee/3L2DK2Uw5F,https://shope.ee/3pyTuxT24M,https://shope.ee/3ff3ieTfPL,https://shope.ee/6pc5UTHbyy,https://shope.ee/6fIfIAIFJx,https://shope.ee/7AEvt5GLJ4,https://shope.ee/6zvVgmGye3,https://shope.ee/7UrmHhF4dA,https://shope.ee/7KYM5OFhy9,https://shope.ee/7pUcgJDnxG,https://shope.ee/7fBCU0ERIF,https://shope.ee/5V6hu1Mggq,https://shope.ee/5KnHhiNK1p,https://shope.ee/5pjYIdLQ0w,https://shope.ee/5fQ86KM3Lv,https://shope.ee/6AMOhFK9L2,https://shope.ee/602yUwKmg1,https://shope.ee/6UzF5rIsf8,https://shope.ee/6KfotYJW07,https://shope.ee/9UcqfN7SZk,https://shope.ee/9KJQT485uj,https://shope.ee/9pFh3z6Btq,https://shope.ee/9ewGrg6pEp,https://shope.ee/A9sXSb4vDw,https://shope.ee/9zZ7GI5YYv,https://shope.ee/AUVNrD3eY2,https://shope.ee/AKBxeu4Ht1,https://shope.ee/8A7T4vCXHc,https://shope.ee/7zo2scDAcb,https://shope.ee/8UkJTXBGbi,https://shope.ee/8KQtHEBtwh,https://shope.ee/8pN9s99zvo,https://shope.ee/8f3jfqAdGn,https://shope.ee/9A00Gl8jFu,https://shope.ee/8zga4S9Mat,https://shope.ee/1LH8wMcY9Q,https://shope.ee/1VaZ8fbuoT,https://shope.ee/1ftzKybHTW,https://shope.ee/1qDPXHae8Z,https://shope.ee/20Wpjaa0nc,https://shope.ee/2AqFvtZNSf,https://shope.ee/2L9g8CYk7i,https://shope.ee/2VT6KVY6ml,https://shope.ee/llLuhcrI,https://shope.ee/B5BYDgzWL,https://shope.ee/LObkWgMBO,https://shope.ee/Vi1wpfiqR,https://shope.ee/g1S98f5VU,https://shope.ee/qKsLReSAX,https://shope.ee/10eIXkdopa,https://shope.ee/1Axik3dBUd,https://shope.ee/40Hu7GSOkC,https://shope.ee/4AbKJZRlPF,https://shope.ee/4KukVsR84I,https://shope.ee/4VEAiBQUjL,https://shope.ee/4fXauUPrOO,https://shope.ee/4pr16nPE3R,https://shope.ee/50ARJ6OaiU,https://shope.ee/5ATrVPNxNX,https://shope.ee/2fmWWoXTS4,https://shope.ee/2q5wj7Wq77,https://shope.ee/30PMvQWCmA,https://shope.ee/3Ain7jVZRD,https://shope.ee/3L2DK2Uw6G,https://shope.ee/3VLdWLUIlJ,https://shope.ee/3ff3ieTfQM,https://shope.ee/3pyTuxT25P,https://shope.ee/6fIfIAIFKy,https://shope.ee/6pc5UTHc01,https://shope.ee/6zvVgmGyf4,https://shope.ee/7AEvt5GLK7,https://shope.ee/7KYM5OFhzA,https://shope.ee/7UrmHhF4eD,https://shope.ee/7fBCU0ERJG,https://shope.ee/7pUcgJDnyJ,https://shope.ee/5KnHhiNK2q,https://shope.ee/5V6hu1Mght,https://shope.ee/5fQ86KM3Mw,https://shope.ee/5pjYIdLQ1z,https://shope.ee/602yUwKmh2,https://shope.ee/6AMOhFK9M5,https://shope.ee/6KfotYJW18,https://shope.ee/6UzF5rIsgB,https://shope.ee/9KJQT485vk,https://shope.ee/9UcqfN7San,https://shope.ee/9ewGrg6pFq,https://shope.ee/9pFh3z6But,https://shope.ee/2L9g87AZQM,https://shope.ee/2VT6KQ9w5P,https://shope.ee/2fmWWj9IkS,https://shope.ee/2q5wj28fPV,https://shope.ee/30PMvL824Y,https://shope.ee/3Ain7e7Ojb,https://shope.ee/3L2DJx6lOe,https://shope.ee/3VLdWG683h,https://shope.ee/3ff3iZ5Uik,https://shope.ee/3pyTus4rNn,https://shope.ee/40Hu7B4E2q,https://shope.ee/4AbKJU3aht,https://shope.ee/4KukVn2xMw,https://shope.ee/4VEAi62K1z,https://shope.ee/4fXauP1gh2,https://shope.ee/4pr16i13M5,https://shope.ee/50ARJ10Q18,https://shope.ee/5ATrVJzmgB,https://shope.ee/5KnHhcz9LE,https://shope.ee/5V6htvyW0H,https://shope.ee/5fQ86ExsfK,https://shope.ee/5pjYIXxFKN,https://shope.ee/602yUqwbzQ,https://shope.ee/6AMOh9vyeT,https://shope.ee/6KfotSvLJW,https://shope.ee/6UzF5luhyZ,https://shope.ee/6fIfI4u4dc,https://shope.ee/6pc5UNtRIf,https://shope.ee/6zvVggsnxi,https://shope.ee/7AEvszsAcl,https://shope.ee/7KYM5IrXHo,https://shope.ee/7UrmHbqtwr,https://shope.ee/7fBCTuqGbu,https://shope.ee/7pUcgDpdGx,https://shope.ee/7zo2sWozw0,https://shope.ee/8A7T4poMb3,https://shope.ee/8KQtH8njG6,https://shope.ee/8UkJTRn5v9,https://shope.ee/8f3jfkmSaC,https://shope.ee/8pN9s3lpFF,https://shope.ee/8zga4MlBuI,https://shope.ee/9A00GfkYZL,https://shope.ee/9KJQSyjvEO,https://shope.ee/9UcqfHjHtR,https://shope.ee/9ewGraieYU,https://shope.ee/9pFh3ti1DX,https://shope.ee/9zZ7GChNsa,https://shope.ee/A9sXSVgkXd,https://shope.ee/AKBxeog7Cg,https://shope.ee/AUVNr7fTrj,https://shope.ee/B5BY8Iopk,https://shope.ee/llLpJSAj,https://shope.ee/Vi1wkHY9q,https://shope.ee/LObkRIBUp,https://shope.ee/qKsLMGHTw,https://shope.ee/g1S93Guov,https://shope.ee/1AxijyF0o2,https://shope.ee/10eIXfFe91,https://shope.ee/1VaZ8aDk88,https://shope.ee/1LH8wHENT7,https://shope.ee/1qDPXCCTSE,https://shope.ee/1ftzKtD6nD,https://shope.ee/2AqFvoBCmK,https://shope.ee/20WpjVBq7J,https://shope.ee/2VT6KQ9w6Q,https://shope.ee/2L9g87AZRP,https://shope.ee/2q5wj28fQW,https://shope.ee/2fmWWj9IlV,https://shope.ee/3Ain7e7Okc,https://shope.ee/30PMvL825b,https://shope.ee/3VLdWG684i,https://shope.ee/3L2DJx6lPh,https://shope.ee/3pyTus4rOo,https://shope.ee/3ff3iZ5Ujn,https://shope.ee/4AbKJU3aiu,https://shope.ee/40Hu7B4E3t,https://shope.ee/4VEAi62K30,https://shope.ee/4KukVn2xNz,https://shope.ee/4pr16i13N6,https://shope.ee/4fXauP1gi5,https://shope.ee/5ATrVJzmhC,https://shope.ee/50ARJ10Q2B,https://shope.ee/5V6htvyW1I,https://shope.ee/5KnHhcz9MH,https://shope.ee/5pjYIXxFLO,https://shope.ee/5fQ86ExsgN,https://shope.ee/6AMOh9vyfU,https://shope.ee/602yUqwc0T,https://shope.ee/6UzF5luhza,https://shope.ee/6KfotSvLKZ,https://shope.ee/6pc5UNtRJg,https://shope.ee/6fIfI4u4ef,https://shope.ee/7AEvszsAdm,https://shope.ee/6zvVggsnyl,https://shope.ee/7UrmHbqtxs,https://shope.ee/7KYM5IrXIr,https://shope.ee/7pUcgDpdHy,https://shope.ee/7fBCTuqGcx,https://shope.ee/8A7T4poMc4,https://shope.ee/7zo2sWozx3,https://shope.ee/20WpjYS1J5,https://shope.ee/1qDPXFSee4,https://shope.ee/1ftzKwTHz3,https://shope.ee/1VaZ8dTvK2,https://shope.ee/1LH8wKUYf1,https://shope.ee/1Axik1VC00,https://shope.ee/10eIXiVpKz,https://shope.ee/qKsLPWSfy,https://shope.ee/g1S96X60x,https://shope.ee/Vi1wnXjLw,https://shope.ee/LObkUYMgv,https://shope.ee/B5BYBZ01u,https://shope.ee/llLsZdMt,https://shope.ee/5ATrVNFxsu,https://shope.ee/50ARJ4GbDt,https://shope.ee/4pr16lHEYs,https://shope.ee/4fXauSHrtr,https://shope.ee/4VEAi9IVEq,https://shope.ee/4KukVqJ8Zp,https://shope.ee/4AbKJXJluo,https://shope.ee/40Hu7EKPFn,https://shope.ee/3pyTuvL2am,https://shope.ee/3ff3icLfvl,https://shope.ee/3VLdWJMJGk,https://shope.ee/3L2DK0Mwbj,https://shope.ee/3Ain7hNZwi,https://shope.ee/30PMvOODHh,https://shope.ee/2q5wj5Oqcg,https://shope.ee/2fmWWmPTxf,https://shope.ee/7pUcgH5oTg,https://shope.ee/7fBCTy6Rof,https://shope.ee/7UrmHf759e,https://shope.ee/7KYM5M7iUd,https://shope.ee/7AEvt38Lpc,https://shope.ee/6zvVgk8zAb,https://shope.ee/6pc5UR9cVa,https://shope.ee/6fIfI8AFqZ,https://shope.ee/6UzF5pAtBY,https://shope.ee/6KfotWBWWX,https://shope.ee/6AMOhDC9rW,https://shope.ee/602yUuCnCV,https://shope.ee/5pjYIbDQXU,https://shope.ee/5fQ86IE3sT,https://shope.ee/5V6htzEhDS,https://shope.ee/5KnHhgFKYR,https://shope.ee/AUVNrAvf4S,https://shope.ee/AKBxerwIPR,https://shope.ee/A9sXSYwvkQ,https://shope.ee/9zZ7GFxZ5P,https://shope.ee/9pFh3wyCQO,https://shope.ee/9ewGrdyplN,https://shope.ee/9UcqfKzT6M,https://shope.ee/9KJQT206RL,https://shope.ee/9A00Gj0jmK,https://shope.ee/8zga4Q1N7J,https://shope.ee/8pN9s720SI,https://shope.ee/8f3jfo2dnH,https://shope.ee/8UkJTV3H8G,https://shope.ee/8KQtHC3uTF,https://shope.ee/8A7T4t4XoE,https://shope.ee/7zo2sa5B9D,https://shope.ee/2L9g8AQke8,https://shope.ee/2VT6KTQ7JB,https://shope.ee/20WpjYS1K6,https://shope.ee/2AqFvrRNz9,https://shope.ee/1ftzKwTI04,https://shope.ee/1qDPXFSef7,https://shope.ee/1LH8wKUYg2,https://shope.ee/1VaZ8dTvL5,https://shope.ee/10eIXiVpM0,https://shope.ee/1Axik1VC13,https://shope.ee/g1S96X61y,https://shope.ee/qKsLPWSh1,https://shope.ee/LObkUYMhw,https://shope.ee/Vi1wnXjMz,https://shope.ee/llLsZdNu,https://shope.ee/B5BYBZ02x,https://shope.ee/50ARJ4GbEu,https://shope.ee/5ATrVNFxtx,https://shope.ee/4fXauSHrus,https://shope.ee/4pr16lHEZv,https://shope.ee/4KukVqJ8aq,https://shope.ee/4VEAi9IVFt,https://shope.ee/40Hu7EKPGo,https://shope.ee/4AbKJXJlvr,https://shope.ee/3ff3icLfwm,https://shope.ee/3pyTuvL2bp,https://shope.ee/3L2DK0Mwck,https://shope.ee/3VLdWJMJHn,https://shope.ee/30PMvOODIi,https://shope.ee/3Ain7hNZxl,https://shope.ee/2fmWWmPTyg,https://shope.ee/2q5wj5Oqdj,https://shope.ee/7fBCTy6Rpg,https://shope.ee/7pUcgH5oUj,https://shope.ee/7KYM5M7iVe,https://shope.ee/7UrmHf75Ah,https://shope.ee/6zvVgk8zBc,https://shope.ee/7AEvt38Lqf,https://shope.ee/6fIfI8AFra",
    "mainURL": "https://mayinmavachhcm.blogspot.com/p/apkmoddone-get-key.html"
}
